[
    {
        "ParameterKey":"EnvName",
        "ParameterValue":"${env}"
    },
    {
        "ParameterKey":"Ec2InstanceKeyname",
        "ParameterValue":"${Ec2InstanceKeyname}"
    },
    {
        "ParameterKey":"WebInstanceSize",
        "ParameterValue":"${WebInstanceSize}"
    },
    {
        "ParameterKey":"WorkerInstanceSize",
        "ParameterValue":"${WorkerInstanceSize}"
    },
    {
        "ParameterKey":"DbInstanceSize",
        "ParameterValue":"${DbInstanceSize}"
    },
    {
        "ParameterKey":"WebInstanceMin",
        "ParameterValue":"${WebInstanceMin}"
    },
    {
        "ParameterKey":"WebInstanceMax",
        "ParameterValue":"${WebInstanceMax}"
    },
    {
        "ParameterKey":"WebInstanceIncrement",
        "ParameterValue":"${WebInstanceIncrement}"
    },
    {
        "ParameterKey":"WorkerInstanceMin",
        "ParameterValue":"${WorkerInstanceMin}"
    },
    {
        "ParameterKey":"WorkerInstanceMax",
        "ParameterValue":"${WorkerInstanceMax}"
    },
    {
        "ParameterKey":"WorkerInstanceIncrement",
        "ParameterValue":"${WorkerInstanceIncrement}"
    },
    {
        "ParameterKey":"DnsZoneId",
        "ParameterValue":"${DnsZoneId}"
    },
    {
        "ParameterKey":"DnsZoneName",
        "ParameterValue":"${DnsZoneName}"
    },
    {
        "ParameterKey":"DBMasterUserName",
        "ParameterValue":"${DBMasterUserName}"
    },
    {
        "ParameterKey":"DBMasterUserPassword",
        "ParameterValue":"${DBMasterUserPassword}"
    },
    {
        "ParameterKey":"DBName",
        "ParameterValue":"${DBName}"
    },
    {
        "ParameterKey":"DBSnapshotARNRestore",
        "ParameterValue":"${DBSnapshotARNRestore}"
    },
    {
        "ParameterKey":"MQUsername",
        "ParameterValue":"${MQUsername}"
    },
    {
        "ParameterKey":"MQPassword",
        "ParameterValue":"${MQPassword}"
    },
    {
        "ParameterKey":"SourceBucketName",
        "ParameterValue":"${SourceBucketName}"
    },
    {
        "ParameterKey":"SourcePathWeb",
        "ParameterValue":"${SourcePathWeb}"
    },
    {
        "ParameterKey":"SourcePathWorker",
        "ParameterValue":"${SourcePathWorker}"
    },
    {
        "ParameterKey":"WebVersion",
        "ParameterValue":"${WebVersion}"
    },
    {
        "ParameterKey":"WorkerVersion",
        "ParameterValue":"${WorkerVersion}"
    },
    {
        "ParameterKey":"DbVersion",
        "ParameterValue":"${DbVersion}"
    },
    {
        "ParameterKey":"NotificationsEmail",
        "ParameterValue":"${NotificationsEmail}"
    }, 
    {
        "ParameterKey": "SesEmailRegion",
        "ParameterValue":"${SesEmailRegion}"
    }, 
    {
        "ParameterKey": "H2XEmailAddress",
        "ParameterValue":"${H2XEmailAddress}"
    }, 
    {
        "ParameterKey": "WebHookZapierCreateHubspotContact", 
        "ParameterValue": "${WEBHOOK_ZAPIER_CREATE_HUBSPOT_CONTACT}"
    },
    {
        "ParameterKey": "NewMembersEmail", 
        "ParameterValue": "${NewMembersEmail}"
    },
    {
        "ParameterKey": "BugsEmail", 
        "ParameterValue": "${BugsEmail}"
    },
    {
        "ParameterKey": "FeedbackEmail", 
        "ParameterValue": "${FeedbackEmail}"
    },
    {
        "ParameterKey": "WebAppSSLCert",
        "ParameterValue": "${WEB_APP_SSL_CERT_ARN}"
    },
    {
        "ParameterKey": "CDNLogBucket",
        "ParameterValue": "${CDN_LOG_BUCKET}"
    }
]
